g4l/__init__.py
g4l/g4l.py
g4l/cli_common/app_version.py
g4l/cli_common/argdocs.py
g4l/cli_common/cfg.py
go_for_launch-0.0.0.dist-info/LICENSE
go_for_launch-0.0.0.dist-info/METADATA
go_for_launch-0.0.0.dist-info/WHEEL
go_for_launch-0.0.0.dist-info/entry_points.txt
go_for_launch-0.0.0.dist-info/top_level.txt
go_for_launch-0.0.0.dist-info/RECORD
