Metadata-Version: 2.1
Name: go-for-launch
Version: 0.0.0
Summary: A generic minimalistic launcher implemented as a python CLI
Author-email: Dan Kamrath <dmkamrath@gmail.com>
License: Copyright (c) 2024 Dan Kamrath
Classifier: Programming Language :: Python :: 3
Classifier: License :: OSI Approved :: MIT License
Classifier: Operating System :: OS Independent
Requires-Python: >=3.8
License-File: LICENSE
Requires-Dist: boto3
